src/__init__.py
src/aws_credentials.py
src/commands.py
src/configuration.py
src/file_processor.py
src/kibana.py
src/utils/__init__.py
src/utils/dashboard.py
src/utils/metric.py
src/utils/table.py
src/utils/visualization.py
tests/__init__.py
tests/helpers.py
tests/unit/__init__.py
tests/unit/test_aws_credentials.py
tests/unit/test_commands.py
tests/unit/test_file_processor.py
tests/unit/test_kibana.py
tests/unit/utils/__init__.py
tests/unit/utils/test_dashboard.py
tests/unit/utils/test_metric.py
tests/unit/utils/test_table.py
tests/unit/utils/test_visualization.py
logger_to_kibana-0.8.2.dist-info/LICENSE
logger_to_kibana-0.8.2.dist-info/METADATA
logger_to_kibana-0.8.2.dist-info/WHEEL
logger_to_kibana-0.8.2.dist-info/entry_points.txt
logger_to_kibana-0.8.2.dist-info/top_level.txt
logger_to_kibana-0.8.2.dist-info/RECORD
