Metadata-Version: 2.1
Name: logger-to-kibana
Version: 0.8.2
Summary: Import logger messages from a file and                  generates a Kibana Visualization
Home-page: https://github.com/ismaelmartinez/logger-to-kibana
Author: Ismael Martinez Ramos
Author-email: ismaelmartinez@gmail.com
License: MIT
Platform: UNKNOWN
Classifier: Programming Language :: Python :: 3.7
Classifier: License :: OSI Approved :: MIT License
Classifier: Operating System :: OS Independent
